setup.py
fed_shap/__init__.py
fed_shap/fed_shap.py
fed_shap.egg-info/PKG-INFO
fed_shap.egg-info/SOURCES.txt
fed_shap.egg-info/dependency_links.txt
fed_shap.egg-info/not-zip-safe
fed_shap.egg-info/top_level.txt