Metadata-Version: 2.1
Name: fed-shap
Version: 1.0.2
Summary: Calculates shapley values
Author: Muhammad Usman Asgher
